isinstancex/__init__.py
isinstancex/_version.py
isinstancex/isinstancex.py
isinstancex/parser.py
isinstancex-2.0.0.dist-info/LICENSE
isinstancex-2.0.0.dist-info/METADATA
isinstancex-2.0.0.dist-info/WHEEL
isinstancex-2.0.0.dist-info/top_level.txt
isinstancex-2.0.0.dist-info/RECORD
