Metadata-Version: 2.1
Name: isinstancex
Version: 2.0.0
Summary: Extend isinstance function
Home-page: https://github.com/DuelitDev/isinstancex
Author: DuelitDev
Author-email: jyoon07dev@gmail.com
Maintainer: DuelitDev
Maintainer-email: jyoon07dev@gmail.com
Keywords: isinstance,isinstancex
Classifier: License :: OSI Approved :: MIT License
Classifier: Programming Language :: Python :: 3.8
Classifier: Programming Language :: Python :: 3.9
Classifier: Programming Language :: Python :: 3.10
Classifier: Programming Language :: Python :: 3.11
Requires-Python: >=3.8
License-File: LICENSE
